{
  "index": 94,
  "author": "加能作次郎",
  "title": "恭三の父",
  "summary": "『恭三の父』は、恭三という若者が故郷の村で過ごす日常を描いた作品です。物語は、恭三が帰省してからの単調な生活に苦しむ様子から始まります。彼は友達もおらず、勉強もできず、毎日手紙を書いたり村を散歩したりして時間を潰しています。手紙を書くことは、孤独を紛らわせるためでもあり、友達からの返事を期待するためでもあります。\n\nある晩、恭三は家に帰ると、父が手紙を受け取ったことを知りますが、それは自分宛ではなく、家族宛のものでした。父は酔っており、手紙の内容を恭三に詳しく説明してほしいと求めますが、恭三はそれがつまらない内容だと思い、素気ない返事をします。これに父は不満を抱き、恭三との間に微妙な緊張が生まれます。\n\n物語は、父と恭三の間のコミュニケーションの難しさや、父の無学さに対する恭三の思い、そして父の酔った時の感情の表れを描写します。父は酔っているときに自分の真情を吐露し、恭三に対して不平を言ったり、教訓めいたことを述べたりしますが、恭三はその意図を理解しつつも、どう反応すべきか悩みます。\n\n物語の後半では、村の祭りの様子が描かれ、父が酔っ払って帰ってくる場面が描かれます。父は祭りの話をしながら、恭三や弟の浅七と共に過ごしますが、酔っているために話が冗長になり、最終的には眠り込んでしまいます。恭三は父の喜ぶ姿を見ながら、彼の心情を理解しようと努めますが、同時に父との距離感も感じています。\n\nこの作品は、家族の絆やコミュニケーションの難しさ、そして日常生活の中での人間関係の微妙な感情を描いています。特に、父と息子の関係に焦点を当て、無学な父親の心情や、恭三の内面的な葛藤を通じて、家族の愛情や理解の重要性が伝わってきます。",
  "url": "https://www.aozora.gr.jp/cards/000247/files/1333_20664.html"
}
